{
  "stat": {
    "mean_testregion": "Durchschnitt Testregion",
    "sig.": "sig.",
    "non-sig.": "nicht sig.",
    "significant": "statistisch signifikant",
    "not_significant": "nicht statistisch signifikant",
    "unadjusted": "unkontrolliert",
    "adjusted": "kontrolliert",
    "controlled": "statistisch kontrolliert",
    "uncontrolled": "unkontrolliert",
    "overall_mean": "Gesamtergebnis Schweiz",
    "cantonal_mean": "Gesamtergebnis Kanton",
    "CH_OVERALL": "{{stat/overall_mean}}",
    "mean": "Mittelwert",
    "median": "Median",
    "sd": "Standardabweichung",
    "variance": "Varianz",
    "min": "Minimum",
    "max": "Maximum",
    "range": "Spannweite",
    "percentile": "Perzentil",
    "quartile": "Quartil / Quartile (erstes Quartil, zweites, drittes, viertes; 1. Quartil, 2., 3., 4.)",
    "iqr": "Interquartilsabstand",
    "difference": "Differenz",
    "mean_difference": "Mittelwertsdifferenz",
    "percentage_point_difference": "Prozentpunktdifferenz",
    "contrast": "Kontrast",
    "gap": "Abstand",
    "comparison": "Vergleich",
    "higher_than": "höher als",
    "lower_than": "tiefer als",
    "no_difference": "kein Unterschied",
    "p_value": "p-Wert",
    "alpha": "Signifikanzniveau",
    "confidence_interval": "Konfidenzintervall",
    "ci_lower": "untere Grenze des Konfidenzintervalls",
    "ci_upper": "obere Grenze des Konfidenzintervalls",
    "standard_error": "Standardfehler",
    "effect_size": "Effektstärke",
    "cohens_d": "Cohen's d",
    "hedges_g": "Hedges' g",
    "eta_squared": "Eta-Quadrat",
    "odds_ratio": "Odds Ratio",
    "risk_ratio": "Risikoverhältnis",
    "small_effect": "kleiner Effekt",
    "medium_effect": "mittlerer Effekt",
    "large_effect": "grosser Effekt",
    "model": "Modell",
    "regression": "Regression",
    "bivariate": "bivariat",
    "multivariate": "multivariat",
    "covariate": "Kovariate",
    "fixed_effects": "Fixe Effekte",
    "random_effects": "Zufällige Effekte",
    "sample": "Stichprobe",
    "population": "Population",
    "sample_size": "Stichprobengrösse",
    "weighted": "gewichtet",
    "unweighted": "ungewichtet",
    "sampling_weight": "Stichprobengewicht",
    "replicate_weight": "Replikationsgewicht",
    "measurement_error": "Messfehler",
    "PPS": "PPS-Verfahren",
    "mixed_design": "gemischtes Design",
    "school_census": "Schulzensus",
    "design": "Stichprobendesign",
    "sc_excl_rate": "Ausschlussquote\nauf Schulebene",
    "st_excl_rate": "Ausschlussquote\nauf Schüler-/innenebene",
    "sc_resp_rate": "Rücklaufquote\nauf Schulebene",
    "st_resp_rate": "Rücklaufquote\nauf Schüler-/innenebene",
    "sc_n_tested": "Anzahl erhobener\nSchulen",
    "st_n": "Anzahl erhobener\nSchülerinnen und Schüler",
    "ugk_sample_size": "ÜGK-Populationsumfang",
    "coverage": "Ausschöpfungsquote",
    "sc_ss_realized": "Anzahl teilnehmender\nSchülerinnen und Schüler\n(realisierte Stichprobe)",
    "total": "TOTAL",
    "difference_description": "Bezeichnung des Unterschieds",
    "difference_result": "Unterschied und Signifikanz",
    "rand_sampling": "Zufallsverfahren",
    "quartile2_low_ch": "Zweitunterste 25% Gesamtschweiz",
    "quartile2_high_ch": "Zweitoberste 25% Gesamtschweiz",
    "comparable_samples": "vergleichbare Stichproben",
    "data_random": "Daten und Zufall",
    "data_analysis": "Datenanalyse",
    "data_eval": "Auswertung",
    "multilevel_analysis": "Mehrebenenanalyse",
    "validity_checks": "Validitätskontrollen",
    "correlation": "Korrelation",
    "resp_rate": "Ausschöpfungsquote",
    "cohen_d_effect": "Cohens d für statistisch signifikante Unterschiede",
    "rand_principle": "Zufallsprinzip",
    "assess_duration": "Erhebungszeit",
    "effect_small_med": "kleine bis mittelgrosse Effekte",
    "sampling_design": "Stichprobendesign",
    "std_dev": "Standardabweichung",
    "samples_alt": "Stichproben",
    "rand_sample": "Zufallsstichprobe",
    "cant_extra_samples": "kantonale Zusatzstichproben",
    "cluster_effects": "Klumpeneffekte",
    "samp_error": "Stichprobenfehler (Standardfehler)",
    "std_error": "Standardfehler",
    "stu_population_est": "Geschätzte Population der Schülerinnen und Schüler des 8. / 11. Schuljahres HarmoS",
    "conf_interval": "Konfidenzintervall",
    "swiss_mean": "der Schweizer Mittelwert",
    "data_weight_analysis": "Gewichtung und Auswertung der erhobenen Daten",
    "two_stage_design": "zweistufiges Verfahren (Schulen und Schüler/-innen)",
    "two_stage_sampling": "zweistufiges Ziehungsverfahren",
    "one_two_stage_sampling": "ein- oder zweistufiges Ziehungsverfahren",
    "stu_sampling": "Ziehung der Schülerinnen und Schüler",
    "target_pops": "Zielpopulationen",
    "sample_prep": "Vorbereitung der Stichproben",
    "quartile_low_ch": "Unterste 25% Gesamtschweiz",
    "quartile_high_ch": "Oberste 25% Gesamtschweiz",
    "census_assess": "Vollerhebung",
    "rand_sampling_proc": "zufällige Stichprobenziehung",
    "stat_significance": "Statistische Signifikanz und Bedeutsamkeit",
    "statistics": "Statistik",
    "stratification": "Schichtung",
    "ugk_population_size": "ÜGK-Populationsumfang",
    "sch_resp_rate": "Rücklaufquote auf Schulebene",
    "stu_part_rate": "Teilnahmequote der Schülerinnen und Schüler",
    "stu_exclusion_rate": "Ausschlussquote auf Schülerbene",
    "sch_exclusion_rate": "Ausschlussquote auf Schulebene",
    "sampling": "Stichprobenziehung",
    "age_sample": "Altersstichprobe",
    "rand_sch_sample": "zufällig gezogene Schulstichprobe",
    "validation_weighting": "Validierung und Gewichtung",
    "variable": "Variable"
  }
}
